lanzou/__init__.py
lanzou/api/__init__.py
lanzou/api/core.py
lanzou/api/models.py
lanzou/api/types.py
lanzou/api/utils.py
lanzou_windfollowingheart/__init__.py
lanzou_windfollowingheart/api/__init__.py
lanzou_windfollowingheart/api/core.py
lanzou_windfollowingheart/api/models.py
lanzou_windfollowingheart/api/types.py
lanzou_windfollowingheart/api/utils.py
lanzou_api_windfollowingheart-1.0.3.dist-info/LICENSE
lanzou_api_windfollowingheart-1.0.3.dist-info/METADATA
lanzou_api_windfollowingheart-1.0.3.dist-info/WHEEL
lanzou_api_windfollowingheart-1.0.3.dist-info/top_level.txt
lanzou_api_windfollowingheart-1.0.3.dist-info/RECORD
