Metadata-Version: 2.2
Name: lanzou-api-windfollowingheart
Version: 1.0.3
Summary: LanZouCloud API
Home-page: https://github.com/windfollowingheart/LanZouCloud-API
Author: zaxtyson, follower: windfollowingheart
Author-email: 2916311184@qq.com
Classifier: Programming Language :: Python :: 3
Classifier: Operating System :: OS Independent
License-File: LICENSE
Requires-Dist: requests
Requires-Dist: requests_toolbelt
Dynamic: author
Dynamic: author-email
Dynamic: classifier
Dynamic: description
Dynamic: description-content-type
Dynamic: home-page
Dynamic: requires-dist
Dynamic: summary
